snakemake_storage_plugin_apd/__init__.py
snakemake_storage_plugin_apd-0.1.4.dist-info/METADATA
snakemake_storage_plugin_apd-0.1.4.dist-info/WHEEL
snakemake_storage_plugin_apd-0.1.4.dist-info/licenses/LICENSE
snakemake_storage_plugin_apd-0.1.4.dist-info/RECORD
