Metadata-Version: 2.4
Name: snakemake-storage-plugin-apd
Version: 0.1.4
Summary: A Snakemake storage plugin for the LHCb apd API.
Project-URL: Source code, https://github.com/snakemake/snakemake-storage-plugin-apd
Project-URL: Documentation, https://snakemake.github.io/snakemake-plugin-catalog/plugins/storage/apd.html
Author-email: Chris Burr <christopher.burr@cern.ch>, Matthew Monk <matthew.david.monk@cern.ch>
License-File: LICENSE
Requires-Python: >=3.11
Requires-Dist: apd<1.0,>=0.8.1
Requires-Dist: snakemake-interface-common<2,>=1.15.0
Requires-Dist: snakemake-interface-storage-plugins<5,>=4.1
Requires-Dist: xrootd<6,>=5.6
